{
  "version-0.20.0-docs": {
    "Introduction": [
      "version-0.20.0-accordproject",
      "version-0.20.0-accordproject-concepts",
      "version-0.20.0-accordproject-business",
      "version-0.20.0-accordproject-developers"
    ],
    "Getting Started": [
      "version-0.20.0-started-installation",
      "version-0.20.0-started-hello",
      "version-0.20.0-started-studio",
      "version-0.20.0-started-resources"
    ],
    "User Tutorials": [
      {
        "type": "subcategory",
        "label": "Authoring with Template Studio",
        "ids": [
          "version-0.20.0-tutorial-latedelivery"
        ]
      },
      {
        "type": "subcategory",
        "label": "Work with Cicero",
        "ids": [
          "version-0.20.0-tutorial-templates",
          "version-0.20.0-tutorial-library",
          "version-0.20.0-tutorial-create"
        ]
      }
    ],
    "Developers Tutorials": [
      {
        "type": "subcategory",
        "label": "Template Execution",
        "ids": [
          "version-0.20.0-tutorial-nodejs",
          "version-0.20.0-tutorial-hyperledger"
        ]
      }
    ],
    "Template Guides": [
      {
        "type": "subcategory",
        "label": "CiceroMark",
        "ids": [
          "version-0.20.0-markup-cicero",
          "version-0.20.0-markup-commonmark",
          "version-0.20.0-markup-variables",
          "version-0.20.0-markup-blocks",
          "version-0.20.0-markup-ergo"
        ]
      },
      {
        "type": "subcategory",
        "label": "Concerto Modeling",
        "ids": [
          "version-0.20.0-model-concerto",
          "version-0.20.0-model-namespaces",
          "version-0.20.0-model-classes",
          "version-0.20.0-model-enums",
          "version-0.20.0-model-properties",
          "version-0.20.0-model-relationships",
          "version-0.20.0-model-decorators",
          "version-0.20.0-model-api"
        ]
      },
      {
        "type": "subcategory",
        "label": "Ergo Logic",
        "ids": [
          "version-0.20.0-logic-ergo",
          "version-0.20.0-logic-simple-expr",
          "version-0.20.0-logic-simple-type",
          "version-0.20.0-logic-complex-type",
          "version-0.20.0-logic-advanced-expr",
          "version-0.20.0-logic-stmt",
          "version-0.20.0-logic-decl",
          "version-0.20.0-logic-module"
        ]
      }
    ],
    "Reference Manual": [
      "version-0.20.0-ref-glossary",
      "version-0.20.0-ref-testing",
      "version-0.20.0-ref-errors",
      "version-0.20.0-ref-logic",
      "version-0.20.0-ref-logic-stdlib",
      "version-0.20.0-ref-logic-specification",
      {
        "type": "subcategory",
        "label": "Template Migration",
        "ids": [
          "version-0.20.0-ref-migrate-0.13-0.20"
        ]
      },
      {
        "type": "subcategory",
        "label": "Command Line Interface",
        "ids": [
          "version-0.20.0-cicero-cli",
          "version-0.20.0-concerto-cli",
          "version-0.20.0-ergo-cli",
          "version-0.20.0-markus-cli"
        ]
      },
      {
        "type": "subcategory",
        "label": "JavaScript API",
        "ids": [
          "version-0.20.0-cicero-api",
          "version-0.20.0-ergo-api",
          "version-0.20.0-concerto-api"
        ]
      }
    ]
  }
}
