{
  "unversionedId": "ref-ergo-cli",
  "id": "version-0.13/ref-ergo-cli",
  "isDocsHomePage": false,
  "title": "Command Line",
  "description": "Install the @accordproject/ergo-cli npm package to access the Ergo command line interface (CLI). After installation you can use the ergo command and its sub-commands as described below.",
  "source": "@site/versioned_docs/version-0.13/ref-ergo-cli.md",
  "slug": "/ref-ergo-cli",
  "permalink": "/docs/0.13/ref-ergo-cli",
  "version": "0.13",
  "lastUpdatedBy": "Author",
  "lastUpdatedAt": 1539502055
}