{
  "unversionedId": "ref-glossary",
  "id": "ref-glossary",
  "isDocsHomePage": false,
  "title": "Glossary",
  "description": "Variable",
  "source": "@site/../docs/ref-glossary.md",
  "slug": "/ref-glossary",
  "permalink": "/docs/next/ref-glossary",
  "version": "current",
  "lastUpdatedBy": "Matt Roberts",
  "lastUpdatedAt": 1572966134,
  "sidebar": "docs",
  "previous": {
    "title": "With Hyperledger Fabric",
    "permalink": "/docs/next/tutorial-hyperledger"
  },
  "next": {
    "title": "Errors",
    "permalink": "/docs/next/ref-errors"
  }
}