{
  "unversionedId": "spec-concepts",
  "id": "version-0.13/spec-concepts",
  "isDocsHomePage": false,
  "title": "Concepts and High-level Architecture",
  "description": "Overview",
  "source": "@site/versioned_docs/version-0.13/spec-concepts.md",
  "slug": "/spec-concepts",
  "permalink": "/docs/0.13/spec-concepts",
  "version": "0.13",
  "lastUpdatedBy": "Author",
  "lastUpdatedAt": 1539502055,
  "sidebar": "version-0.13/docs",
  "previous": {
    "title": "Overview",
    "permalink": "/docs/0.13/spec-overview"
  },
  "next": {
    "title": "Example: Late Delivery Clause",
    "permalink": "/docs/0.13/spec-example"
  }
}